CirclesGetCountryName/__init__.py
CirclesGetCountryName/opencage_get_country_name.py
OpenCage_local-0.0.1.dist-info/METADATA
OpenCage_local-0.0.1.dist-info/WHEEL
OpenCage_local-0.0.1.dist-info/top_level.txt
OpenCage_local-0.0.1.dist-info/RECORD
