Metadata-Version: 2.1
Name: OpenCage-local
Version: 0.0.1
Summary: PyPI Package for Circles Local OpenCage Python
Home-page: https://github.com/javatechy/dokr
Author: Circles
Author-email: info@circles.life
Classifier: Programming Language :: Python :: 3
Classifier: License :: Other/Proprietary License
Classifier: Operating System :: OS Independent
